ucron/__init__.py
ucron/__main__.py
ucron/cli.py
ucron/conf.py
ucron/db.py
ucron/ext.py
ucron/server.py
ucron/stpl.py
ucron/utils.py
ucron/worker.py
ucron-0.1.3.dist-info/METADATA
ucron-0.1.3.dist-info/RECORD
ucron-0.1.3.dist-info/WHEEL
ucron-0.1.3.dist-info/top_level.txt
