Metadata-Version: 2.1
Name: ucron
Version: 0.1.3
Summary: A micro Crontab & Task Queue for Python Web.
Home-page: http://github.com/akgnah/ucron
Author: Akgnah
Author-email: 1024@setq.me
License: MIT
Keywords: crontab task queue
Platform: any
Requires-Dist: bottle
